pipelineful/__init__.py
pipelineful-0.1.6.dist-info/METADATA
pipelineful-0.1.6.dist-info/WHEEL
pipelineful-0.1.6.dist-info/entry_points.txt
pipelineful-0.1.6.dist-info/RECORD
