Metadata-Version: 2.4
Name: pipelineful
Version: 0.1.6
Summary: Easily create pipelines from excel source!
Author-email: something <something@gmail.ru>
Requires-Python: >=3.12
Requires-Dist: openpyxl>=3.1.5
Requires-Dist: pandas>=2.3.0
Requires-Dist: sqlmodel>=0.0.24
